pptx_templater/__init__.py
pptx_templater/core.py
pptx_templater/file_handler.py
pptx_templater/slides.py
pptx_templater/text_parser.py
python_pptx_templater-1.1.15.dist-info/LICENSE
python_pptx_templater-1.1.15.dist-info/METADATA
python_pptx_templater-1.1.15.dist-info/WHEEL
python_pptx_templater-1.1.15.dist-info/top_level.txt
python_pptx_templater-1.1.15.dist-info/RECORD
